schemix_mypy/__init__.py
schemix_mypy/py.typed
schemix_mypy/select_handler.py
schemix_mypy-0.1.0a0.dist-info/METADATA
schemix_mypy-0.1.0a0.dist-info/WHEEL
schemix_mypy-0.1.0a0.dist-info/RECORD
