Metadata-Version: 2.4
Name: schemix-mypy
Version: 0.1.0a0
Summary: Add your description here
Author-email: Ethan Coward <ethan@ethancoward.dev>
Requires-Python: >=3.13
Requires-Dist: mypy>=1.16.0
